tree_sitter_puppet/__init__.py
tree_sitter_puppet/_binding.abi3.so
tree_sitter_puppet/binding.c
tree_sitter_puppet/__init__.pyi
tree_sitter_puppet/py.typed
tree_sitter_puppet/queries/folds.scm
tree_sitter_puppet/queries/highlights.scm
tree_sitter_puppet/queries/indents.scm
tree_sitter_puppet/queries/injections.scm
tree_sitter_puppet/queries/locals.scm
tree_sitter_puppet-1.3.0.dist-info/top_level.txt
tree_sitter_puppet-1.3.0.dist-info/RECORD
tree_sitter_puppet-1.3.0.dist-info/LICENSE
tree_sitter_puppet-1.3.0.dist-info/METADATA
tree_sitter_puppet-1.3.0.dist-info/WHEEL
